{"0": {"traceId": "1681b804bdbd19a1", "timestamp_start": "2020-08-31 11:36:43.423262", "timestamp_stop": "2020-08-31 11:37:01.196983", "duration": "17773.721", "response": {"activationId": "bba85ec65cd14d9ca85ec65cd1cd9c35", "annotations": [{"key": "topmost", "value": true}, {"key": "path", "value": "guest/productUpdate"}, {"key": "kind", "value": "sequence"}, {"key": "limits", "value": {"concurrency": 1, "logs": 10, "memory": 128, "timeout": 60000}}], "duration": 7972, "end": 1598866621188, "logs": ["07cdf771588149c58df771588149c51c", "a8b58b46ec6d4377b58b46ec6d037773"], "name": "productUpdate", "namespace": "guest", "publish": false, "response": {"result": {"__OW_TRACE_ID": "1681b804bdbd19a1", "execTime": 5.696758270263672, "message": "successful"}, "size": 89, "status": "success", "success": true}, "start": 1598866603567, "subject": "guest", "version": "0.0.1"}, "input": {"shopKey": "771d87188d568ddd", "csvUrl": "http://130.149.158.232:9990/productdata/products.csv"}, "activationListEntry": {"activationId": "bba85ec65cd14d9ca85ec65cd1cd9c35", "annotations": [{"key": "topmost", "value": true}, {"key": "path", "value": "guest/productUpdate"}, {"key": "kind", "value": "sequence"}, {"key": "limits", "value": {"concurrency": 1, "logs": 10, "memory": 128, "timeout": 60000}}], "duration": 17621, "end": 1598866621188, "name": "productUpdate", "namespace": "guest", "publish": false, "start": 1598866603567, "statusCode": 0, "version": "0.0.1"}}, "1": {"traceId": null, "timestamp_start": "2020-08-31 11:37:43.426225", "timestamp_stop": "2020-08-31 11:37:43.530905", "duration": "104.68", "response": {"activationId": "34792c724d204982b92c724d20c98285", "annotations": [{"key": "topmost", "value": true}, {"key": "path", "value": "guest/productUpdate"}, {"key": "kind", "value": "sequence"}, {"key": "limits", "value": {"concurrency": 1, "logs": 10, "memory": 128, "timeout": 60000}}], "duration": 5, "end": 1598866663524, "logs": ["df252fd267c543f1a52fd267c503f1ef"], "name": "productUpdate", "namespace": "guest", "publish": false, "response": {"result": {"error": "could not fetch data properly 'NoneType' object has no attribute 'split'"}, "size": 85, "status": "application error", "success": false}, "start": 1598866663451, "subject": "guest", "version": "0.0.1"}, "input": {"shopKey": "771d87188d568ddd", "csvUrl": "http://130.149.158.232:9990/productdata/products.csv"}, "activationListEntry": {"activationId": "34792c724d204982b92c724d20c98285", "annotations": [{"key": "topmost", "value": true}, {"key": "path", "value": "guest/productUpdate"}, {"key": "kind", "value": "sequence"}, {"key": "limits", "value": {"concurrency": 1, "logs": 10, "memory": 128, "timeout": 60000}}], "duration": 73, "end": 1598866663524, "name": "productUpdate", "namespace": "guest", "publish": false, "start": 1598866663451, "statusCode": 1, "version": "0.0.1"}}, "2": {"traceId": "b8957733e1c229cb", "timestamp_start": "2020-08-31 11:38:43.486598", "timestamp_stop": "2020-08-31 11:38:43.956876", "duration": "470.278", "response": {"activationId": "40ce9ad6f734425c8e9ad6f734625c50", "annotations": [{"key": "topmost", "value": true}, {"key": "path", "value": "guest/productUpdate"}, {"key": "kind", "value": "sequence"}, {"key": "limits", "value": {"concurrency": 1, "logs": 10, "memory": 128, "timeout": 60000}}], "duration": 305, "end": 1598866723952, "logs": ["a0163ddccf6c4525963ddccf6c1525c6", "b6495111b4424035895111b442f035e7"], "name": "productUpdate", "namespace": "guest", "publish": false, "response": {"result": {"__OW_TRACE_ID": "b8957733e1c229cb", "execTime": 0.29276084899902344, "message": "successful"}, "size": 91, "status": "success", "success": true}, "start": 1598866723511, "subject": "guest", "version": "0.0.1"}, "input": {"shopKey": "771d87188d568ddd", "csvUrl": "http://130.149.158.232:9990/productdata/products.csv"}, "activationListEntry": {"activationId": "40ce9ad6f734425c8e9ad6f734625c50", "annotations": [{"key": "topmost", "value": true}, {"key": "path", "value": "guest/productUpdate"}, {"key": "kind", "value": "sequence"}, {"key": "limits", "value": {"concurrency": 1, "logs": 10, "memory": 128, "timeout": 60000}}], "duration": 441, "end": 1598866723952, "name": "productUpdate", "namespace": "guest", "publish": false, "start": 1598866723511, "statusCode": 0, "version": "0.0.1"}}, "3": {"traceId": "484f1146063d0a78", "timestamp_start": "2020-08-31 11:39:43.546731", "timestamp_stop": "2020-08-31 11:39:44.204220", "duration": "657.489", "response": {"activationId": "4a587c5974694d68987c597469ed684e", "annotations": [{"key": "topmost", "value": true}, {"key": "path", "value": "guest/productUpdate"}, {"key": "kind", "value": "sequence"}, {"key": "limits", "value": {"concurrency": 1, "logs": 10, "memory": 128, "timeout": 60000}}], "duration": 357, "end": 1598866784199, "logs": ["265524ac7d0440739524ac7d04e07399", "f3cb6f4cc23946ea8b6f4cc23926ea33"], "name": "productUpdate", "namespace": "guest", "publish": false, "response": {"result": {"__OW_TRACE_ID": "484f1146063d0a78", "execTime": 0.34776830673217773, "message": "successful"}, "size": 91, "status": "success", "success": true}, "start": 1598866783569, "subject": "guest", "version": "0.0.1"}, "input": {"shopKey": "771d87188d568ddd", "csvUrl": "http://130.149.158.232:9990/productdata/products.csv"}, "activationListEntry": {"activationId": "4a587c5974694d68987c597469ed684e", "annotations": [{"key": "topmost", "value": true}, {"key": "path", "value": "guest/productUpdate"}, {"key": "kind", "value": "sequence"}, {"key": "limits", "value": {"concurrency": 1, "logs": 10, "memory": 128, "timeout": 60000}}], "duration": 630, "end": 1598866784199, "name": "productUpdate", "namespace": "guest", "publish": false, "start": 1598866783569, "statusCode": 0, "version": "0.0.1"}}, "4": {"traceId": "62cbdd71b6382fce", "timestamp_start": "2020-08-31 11:40:43.606130", "timestamp_stop": "2020-08-31 11:40:44.040935", "duration": "434.805", "response": {"activationId": "5bddcb0e22fe4d8f9dcb0e22fe4d8ff3", "annotations": [{"key": "topmost", "value": true}, {"key": "path", "value": "guest/productUpdate"}, {"key": "kind", "value": "sequence"}, {"key": "limits", "value": {"concurrency": 1, "logs": 10, "memory": 128, "timeout": 60000}}], "duration": 280, "end": 1598866844035, "logs": ["12fd9e103029483bbd9e103029b83bf8", "5c4de360e0d94c678de360e0d91c6772"], "name": "productUpdate", "namespace": "guest", "publish": false, "response": {"result": {"__OW_TRACE_ID": "62cbdd71b6382fce", "execTime": 0.2702920436859131, "message": "successful"}, "size": 90, "status": "success", "success": true}, "start": 1598866843634, "subject": "guest", "version": "0.0.1"}, "input": {"shopKey": "771d87188d568ddd", "csvUrl": "http://130.149.158.232:9990/productdata/products.csv"}, "activationListEntry": {"activationId": "5bddcb0e22fe4d8f9dcb0e22fe4d8ff3", "annotations": [{"key": "topmost", "value": true}, {"key": "path", "value": "guest/productUpdate"}, {"key": "kind", "value": "sequence"}, {"key": "limits", "value": {"concurrency": 1, "logs": 10, "memory": 128, "timeout": 60000}}], "duration": 401, "end": 1598866844035, "name": "productUpdate", "namespace": "guest", "publish": false, "start": 1598866843634, "statusCode": 0, "version": "0.0.1"}}, "5": {"traceId": "eb74612139905075", "timestamp_start": "2020-08-31 11:41:43.614140", "timestamp_stop": "2020-08-31 11:41:44.032574", "duration": "418.434", "response": {"activationId": "97311a5e02724cedb11a5e02722ced4d", "annotations": [{"key": "topmost", "value": true}, {"key": "path", "value": "guest/productUpdate"}, {"key": "kind", "value": "sequence"}, {"key": "limits", "value": {"concurrency": 1, "logs": 10, "memory": 128, "timeout": 60000}}], "duration": 284, "end": 1598866904026, "logs": ["45df5cf4e96b44979f5cf4e96b3497ee", "805b56e54019493c9b56e54019b93c27"], "name": "productUpdate", "namespace": "guest", "publish": false, "response": {"result": {"__OW_TRACE_ID": "eb74612139905075", "execTime": 0.2746620178222656, "message": "successful"}, "size": 90, "status": "success", "success": true}, "start": 1598866903637, "subject": "guest", "version": "0.0.1"}, "input": {"shopKey": "771d87188d568ddd", "csvUrl": "http://130.149.158.232:9990/productdata/products.csv"}, "activationListEntry": {"activationId": "97311a5e02724cedb11a5e02722ced4d", "annotations": [{"key": "topmost", "value": true}, {"key": "path", "value": "guest/productUpdate"}, {"key": "kind", "value": "sequence"}, {"key": "limits", "value": {"concurrency": 1, "logs": 10, "memory": 128, "timeout": 60000}}], "duration": 389, "end": 1598866904026, "name": "productUpdate", "namespace": "guest", "publish": false, "start": 1598866903637, "statusCode": 0, "version": "0.0.1"}}, "6": {"traceId": "d2fbbd1eb286599a", "timestamp_start": "2020-08-31 11:42:43.622200", "timestamp_stop": "2020-08-31 11:42:44.083589", "duration": "461.389", "response": {"activationId": "ceeaba0613b442a6aaba0613b462a604", "annotations": [{"key": "topmost", "value": true}, {"key": "path", "value": "guest/productUpdate"}, {"key": "kind", "value": "sequence"}, {"key": "limits", "value": {"concurrency": 1, "logs": 10, "memory": 128, "timeout": 60000}}], "duration": 263, "end": 1598866964077, "logs": ["b0c6bb3fddf444f886bb3fddf4c4f844", "0b5f1cd5d9ae4fcf9f1cd5d9aeafcff8"], "name": "productUpdate", "namespace": "guest", "publish": false, "response": {"result": {"__OW_TRACE_ID": "d2fbbd1eb286599a", "execTime": 0.2547781467437744, "message": "successful"}, "size": 90, "status": "success", "success": true}, "start": 1598866963642, "subject": "guest", "version": "0.0.1"}, "input": {"shopKey": "771d87188d568ddd", "csvUrl": "http://130.149.158.232:9990/productdata/products.csv"}, "activationListEntry": {"activationId": "ceeaba0613b442a6aaba0613b462a604", "annotations": [{"key": "topmost", "value": true}, {"key": "path", "value": "guest/productUpdate"}, {"key": "kind", "value": "sequence"}, {"key": "limits", "value": {"concurrency": 1, "logs": 10, "memory": 128, "timeout": 60000}}], "duration": 435, "end": 1598866964077, "name": "productUpdate", "namespace": "guest", "publish": false, "start": 1598866963642, "statusCode": 0, "version": "0.0.1"}}, "7": {"traceId": null, "timestamp_start": "2020-08-31 11:43:43.630160", "timestamp_stop": "2020-08-31 11:43:43.969176", "duration": "339.016", "response": {"activationId": "9240caeb3d94434480caeb3d94c34425", "annotations": [{"key": "topmost", "value": true}, {"key": "path", "value": "guest/productUpdate"}, {"key": "kind", "value": "sequence"}, {"key": "limits", "value": {"concurrency": 1, "logs": 10, "memory": 128, "timeout": 60000}}], "duration": 178, "end": 1598867023962, "logs": ["391439dd50a74e059439dd50a7be0575", "badd51ee40524a0a9d51ee4052da0a7e"], "name": "productUpdate", "namespace": "guest", "publish": false, "response": {"result": {"error": "Exception of type: <class 'requests.exceptions.ReadTimeout'>, ErrorMessage: HTTPSConnectionPool(host='130.149.158.143', port=31005): Read timed out. (read timeout=0.0001)"}, "size": 183, "status": "application error", "success": false}, "start": 1598867023657, "subject": "guest", "version": "0.0.1"}, "input": {"shopKey": "771d87188d568ddd", "csvUrl": "http://130.149.158.232:9990/productdata/products.csv"}, "activationListEntry": {"activationId": "9240caeb3d94434480caeb3d94c34425", "annotations": [{"key": "topmost", "value": true}, {"key": "path", "value": "guest/productUpdate"}, {"key": "kind", "value": "sequence"}, {"key": "limits", "value": {"concurrency": 1, "logs": 10, "memory": 128, "timeout": 60000}}], "duration": 305, "end": 1598867023962, "name": "productUpdate", "namespace": "guest", "publish": false, "start": 1598867023657, "statusCode": 1, "version": "0.0.1"}}, "8": {"traceId": "3da1db2277fe205d", "timestamp_start": "2020-08-31 11:44:43.654220", "timestamp_stop": "2020-08-31 11:44:44.060840", "duration": "406.62", "response": {"activationId": "9936a8a8ced24fc3b6a8a8ced28fc3a4", "annotations": [{"key": "topmost", "value": true}, {"key": "path", "value": "guest/productUpdate"}, {"key": "kind", "value": "sequence"}, {"key": "limits", "value": {"concurrency": 1, "logs": 10, "memory": 128, "timeout": 60000}}], "duration": 278, "end": 1598867084056, "logs": ["512ab1695d96401eaab1695d96901ed9", "da0e80f8696c4fba8e80f8696cefbaa4"], "name": "productUpdate", "namespace": "guest", "publish": false, "response": {"result": {"__OW_TRACE_ID": "3da1db2277fe205d", "execTime": 0.2696399688720703, "message": "successful"}, "size": 90, "status": "success", "success": true}, "start": 1598867083675, "subject": "guest", "version": "0.0.1"}, "input": {"shopKey": "771d87188d568ddd", "csvUrl": "http://130.149.158.232:9990/productdata/products.csv"}, "activationListEntry": {"activationId": "9936a8a8ced24fc3b6a8a8ced28fc3a4", "annotations": [{"key": "topmost", "value": true}, {"key": "path", "value": "guest/productUpdate"}, {"key": "kind", "value": "sequence"}, {"key": "limits", "value": {"concurrency": 1, "logs": 10, "memory": 128, "timeout": 60000}}], "duration": 381, "end": 1598867084056, "name": "productUpdate", "namespace": "guest", "publish": false, "start": 1598867083675, "statusCode": 0, "version": "0.0.1"}}, "9": {"traceId": "25dab6c3755bc4ee", "timestamp_start": "2020-08-31 11:45:43.710238", "timestamp_stop": "2020-08-31 11:45:44.163993", "duration": "453.755", "response": {"activationId": "8e036c6b5c51470f836c6b5c51570f73", "annotations": [{"key": "topmost", "value": true}, {"key": "path", "value": "guest/productUpdate"}, {"key": "kind", "value": "sequence"}, {"key": "limits", "value": {"concurrency": 1, "logs": 10, "memory": 128, "timeout": 60000}}], "duration": 275, "end": 1598867144158, "logs": ["95b162ed778f407bb162ed778f307b19", "e1ff915fc1a04362bf915fc1a023624f"], "name": "productUpdate", "namespace": "guest", "publish": false, "response": {"result": {"__OW_TRACE_ID": "25dab6c3755bc4ee", "execTime": 0.26604318618774414, "message": "successful"}, "size": 91, "status": "success", "success": true}, "start": 1598867143775, "subject": "guest", "version": "0.0.1"}, "input": {"shopKey": "771d87188d568ddd", "csvUrl": "http://130.149.158.232:9990/productdata/products.csv"}, "activationListEntry": {"activationId": "8e036c6b5c51470f836c6b5c51570f73", "annotations": [{"key": "topmost", "value": true}, {"key": "path", "value": "guest/productUpdate"}, {"key": "kind", "value": "sequence"}, {"key": "limits", "value": {"concurrency": 1, "logs": 10, "memory": 128, "timeout": 60000}}], "duration": 383, "end": 1598867144158, "name": "productUpdate", "namespace": "guest", "publish": false, "start": 1598867143775, "statusCode": 0, "version": "0.0.1"}}}